{"fr":{"Add new point":"Ajouter un nouveau point","An error occured while reseting the password.":"Une erreur s'est produite lors du changement de mot de passe.","Cancel":"Annuler","Change password":"Changement de mot de passe","Clear":"Réinitialiser","Close":"Fermer","Confirm new password":"Confirmer le nouveau mot de passe","Connect":"Se connecter","Could not change password.":"Impossible de changer le mot de passe.","Could not connect.":"Impossible de ce connecter.","Could not log out.":"Impossible de ce déconnecter.","Logged in as":"Ce connecter en tant que","Logout":"Se déconnecter","New password":"Nouveau mot de passe","OK":"OK","Old password":"Ancien mot de passe","Password":"Mot de passse","Password Changed":"Mot de passe modifié","Password Forgotten?":"Mot de passe oublié?","Password forgotten?":"Mot de passe oublié?","Please, input a login...":"Veillez introduire un nom d'utilisateur...","Search…":"Recherche…","Set as starting point":"Définir le point de départ","Terminate":"Terminer","The old and new passwords are the same.":"L'ancien et le nouveau mot de passe sont identique.","The passwords don't match.":"Les mots de passe ne correspondent pas","Username":"Nom d'utilisateur","Your password has succesfully been changed.":"Votre mot de passe à été modifier avec succès."}}