{"fr":{"Add new point":"Ajouter un nouveau point","An error occured while reseting the password.":"Une erreur s'est produite lors du changement de mot de passe.","Cancel":"Annuler","Change password":"Changer de mot de passe","Clear":"Réinitialiser","Close":"Fermer","Confirm new password":"Confirmer le nouveau mot de passe","Connect":"Se connecter","Could not change password.":"Impossible de changer le mot de passe.","Could not connect.":"Impossible de se connecter.","Could not log out.":"Impossible de se déconnecter.","Logged in as":"Connecté en tant que","Logout":"Se déconnecter","More informations":"Plus d'informations","New password":"Nouveau mot de passe","OK":"OK","Old password":"Ancien mot de passe","Password":"Mot de passe","Password Changed":"Mot de passe modifié","Password forgotten?":"Mot de passe oublié ?","Please, input a login...":"Veuillez introduire un nom d'utilisateur...","Search…":"Recherche…","Set as starting point":"Définir le point de départ","Terminate":"Terminer","The old and new passwords are the same.":"L'ancien et le nouveau mot de passe sont identiques.","The passwords don't match.":"Les mots de passe ne correspondent pas","Username":"Nom d'utilisateur","Your password has succesfully been changed.":"Votre mot de passe a été modifié avec succès.","blank":"Vide","aster":"ASTER","srtm":"SRTM","Mobile Application":"Application mobile","Background":"Fond de carte","Themes":"Thèmes","Measure tools":"Outils de mesure","Login":"Se connecter","Coordinate":"Coordonnée","Length":"Longueur","Enseignement 2":"Enseignement","OSM function":"Fonctions OSM","Edit":"Edition","Group":"Groupe","Layers":"Couches","background":"Fond de carte","test":"Test","test2":"Deuxième test","access":"Acces","aerialway":"Remontée méchanique","amenity":"Equipements","barrier":"Barière","bicycle":"Vélo","brand":"Marque","building":"Batiment","covered":"Couvert","denomination":"Dénomination","display_name":"Nom","ele":"Elévation","foot":"Foot","highway":"Routes","layer":"Couches","leisure":"Loisires","man_made":"Fabrication humaine","motorcar":"Véhicules","name":"Nom","natural":"Naturel","operator":"Opérateur","osm_id":"ID OSM","place":"Place","population":"Population","power":"Energie","railway":"Chemins de fer","ref":"Réference","religion":"Religion","shop":"Magasin","sport":"Sport","surface":"Surface","tourism":"Tourism","waterway":"Cours d'eau","wood":"Bois","open":"Ouvert","timestamp":"Datation","type":"Type","alpine_hut":"Cabane alpine","bank":"Vide","bus_stop":"Arrêt de bus","cafe":"Café","ch.swisstopo.dreiecksvermaschung":"MN95 Maillage triangulaire","ch.swisstopo.geologie-geotechnik-gk500-gesteinsklassierung":"Classification des roches","ch.swisstopo.geologie-geotechnik-gk500-lithologie_hauptgruppen":"Groupes lithologiques","ch.swisstopo.geologie-gravimetrischer_atlas":"Atlas gravimétrique 1:100000","cinema":"Cinéma","firestations":"Caserne de pompiers","fuel":"Station d'essence","hospitals":"Hôpitals","hotel":"Hôtels","information":"Informations","line":"Lignes","osm":"OSM","osm_open":"Temps OSM","osm_scale":"Échelles OSM","osm_time":"Temps OSM","parking":"Parking","place_of_worship":"Lieux de culte","point":"Point","police":"Police","polygon":"Polygon","post_office":"Poste","restaurant":"Restaurants","zoo":"Zoo","asitvd.fond_couleur":"Fond couleur","asitvd.fond_gris":"Fond gris","asitvd.fond_pourortho":"Labels","ch.are.alpenkonvention":"Convention des Alpes","ch.astra.ausnahmetransportrouten":"Itinéraires convois exceptionnels","map":"Carte"}}